job_queue_exporter/__init__.py
job_queue_exporter/main_exporter.py
job_queue_exporter/slurm_parser.py
job_queue_exporter/squeue.py
job_queue_exporter-0.11.dist-info/METADATA
job_queue_exporter-0.11.dist-info/WHEEL
job_queue_exporter-0.11.dist-info/entry_points.txt
job_queue_exporter-0.11.dist-info/top_level.txt
job_queue_exporter-0.11.dist-info/RECORD
