Metadata-Version: 2.1
Name: job-queue-exporter
Version: 0.11
Summary: Prometheus Exporter for job information associated with HPC Scheduler
Home-page: http://gitlab.com/surfprace/cathal
Author: Cathal Corbett
Author-email: cathalcorbett3@gmail.com
License: UNKNOWN
Platform: UNKNOWN
Requires-Dist: argparse
Requires-Dist: prometheus-client
